protobuf_relocate-0.1.dev1.dist-info/METADATA
protobuf_relocate-0.1.dev1.dist-info/WHEEL
protobuf_relocate-0.1.dev1.dist-info/entry_points.txt
protobuf_relocate-0.1.dev1.dist-info/licenses/LICENSE
protobuf_relocate/__init__.py
protobuf_relocate/_version.py
protobuf_relocate/command.py
protobuf_relocate-0.1.dev1.dist-info/RECORD
